comun_mssql_python.py
comun_mssql_python-0.4.dist-info/METADATA
comun_mssql_python-0.4.dist-info/WHEEL
comun_mssql_python-0.4.dist-info/top_level.txt
comun_mssql_python-0.4.dist-info/RECORD
