Metadata-Version: 2.4
Name: comun_mssql_python
Version: 0.4
Requires-Dist: mssql_python
Dynamic: requires-dist
